folder_schema_validator/__init__.py
folder_schema_validator/__main__.py
folder_schema_validator/core.py
folder_schema_validator-0.1.5.dist-info/licenses/LICENSE
folder_schema_validator-0.1.5.dist-info/METADATA
folder_schema_validator-0.1.5.dist-info/WHEEL
folder_schema_validator-0.1.5.dist-info/entry_points.txt
folder_schema_validator-0.1.5.dist-info/top_level.txt
folder_schema_validator-0.1.5.dist-info/RECORD
