Metadata-Version: 2.4
Name: folder-schema-validator
Version: 0.1.5
Summary: A Python tool for validating folder structures against defined schemas with wildcard support
Author-email: Brandons Corner <contact@brandonscorner.com>
License-Expression: MIT
Project-URL: Homepage, https://github.com/brandonscorner/folder-schema-validator
Project-URL: Bug Tracker, https://github.com/brandonscorner/folder-schema-validator/issues
Classifier: Programming Language :: Python :: 3
Classifier: Operating System :: OS Independent
Requires-Python: >=3.7
License-File: LICENSE
Dynamic: license-file
